payload_parser_standalone/rtl/replace_order_decoder.v
// =============================================
// replace_order_decoder.v
// =============================================
//
// Description: Decode Replace Order ('U') ITCH messages.
// Author: RZ
// Start Date: 20250428
//
// Changelog
// =============================================
// [20250428-1] RZ: Initial Replace Order decoder implementation.
// =============================================

`timescale 1ns/1ps

module replace_order_decoder (
    input  wire        clk,
    input  wire        rst_n,
    input  wire        valid,
    input  wire [511:0] payload,

    output reg         replace_order_decoded,
    output reg [63:0]  original_ref,
    output reg [63:0]  new_ref,
    output reg [31:0]  shares
);

wire [7:0] msg_type = payload[511:504];

always @(posedge clk or negedge rst_n) begin
    if (!rst_n) begin
        replace_order_decoded <= 1'b0;
        original_ref <= 64'd0;
        new_ref <= 64'd0;
        shares <= 32'd0;
    end else if (valid && msg_type == "U") begin
        replace_order_decoded <= 1'b1;
        original_ref <= payload[503:440];
        new_ref <= payload[439:376];
        shares <= payload[375:344];
    end else begin
        replace_order_decoded <= 1'b0;
    end
end

endmodule

payload_parser_standalone/rtl/delete_order_decoder.v
// =============================================
// delete_order_decoder.v
// =============================================
//
// Description: Module to decode Delete Order ('D') messages from ITCH payloads.
// Author: RZ
// Start Date: 04172025
// Version: 0.1
//
// Changelog
// =============================================
// [20250428-1] RZ: Initial scaffold of Delete Order payload decoder module.
// =============================================

`timescale 1ns/1ps

module delete_order_decoder (
    input  wire        clk,
    input  wire        rst_n,
    input  wire        valid,
    input  wire [511:0] payload,

    output reg         delete_order_decoded,
    output reg [63:0]  delete_order_ref
);

// Internal signals
wire [7:0] msg_type;
wire [63:0] order_ref;

assign msg_type = payload[511:504];     // Byte 0 (MSB side first) — Message Type
assign order_ref = payload[503:440];    // Bytes 1-8 — Order Reference Number

// Decode logic
always @(posedge clk or negedge rst_n) begin
    if (!rst_n) begin
        delete_order_decoded <= 1'b0;
        delete_order_ref <= 64'd0;
    end else if (valid) begin
        if (msg_type == "D") begin
            delete_order_decoded <= 1'b1;
            delete_order_ref <= order_ref;
        end else begin
            delete_order_decoded <= 1'b0;
            delete_order_ref <= 64'd0;
        end
    end else begin
        delete_order_decoded <= 1'b0;
    end
end

endmodule

payload_parser_standalone/rtl/cancel_order_decoder.v
// =============================================
// cancel_order_decoder.v
// =============================================
//
// Description: Module to decode Cancel Order ('X') messages from ITCH payloads.
// Author: RZ
// Start Date: 04172025
// Version: 0.1
//
// Changelog
// =============================================
// [20250427-1] RZ: Initial version created for Cancel Order payload decoding.
// [20250428-1] RZ: Updated ports and internal signals for dispatcher integration.
// =============================================

`timescale 1ns/1ps

module cancel_order_decoder (
    input  wire        clk,
    input  wire        rst_n,
    input  wire        valid,
    input  wire [511:0] payload,

    output reg         cancel_order_decoded,
    output reg [63:0]  cancel_order_ref,
    output reg [31:0]  cancel_shares
);

// Internal parsing
wire [7:0] msg_type;
assign msg_type = payload[511:504];

always @(posedge clk or negedge rst_n) begin
    if (!rst_n) begin
        cancel_order_decoded <= 1'b0;
        cancel_order_ref <= 64'd0;
        cancel_shares <= 32'd0;
    end else if (valid) begin
        if (msg_type == "X") begin
            cancel_order_decoded <= 1'b1;
            cancel_order_ref <= payload[503:440];
            cancel_shares <= payload[439:408];
        end else begin
            cancel_order_decoded <= 1'b0;
        end
    end else begin
        cancel_order_decoded <= 1'b0;
    end
end

endmodule

payload_parser_standalone/rtl/add_order_decoder.v
// =============================================
// add_order_decoder.v
// =============================================
//
// Description: Module to decode Add Order ('A') messages from ITCH payloads.
// Author: RZ
// Start Date: 04172025
// Version: 0.1
//
// Changelog
// =============================================
// [20250427-1] RZ: Initial version created for Add Order payload decoding.
// [20250428-1] RZ: Updated ports and internal signals for dispatcher integration.
// =============================================

`timescale 1ns/1ps

module add_order_decoder (
    input  wire        clk,
    input  wire        rst_n,
    input  wire        valid,
    input  wire [511:0] payload,

    output reg         add_order_decoded,
    output reg [63:0]  order_ref,
    output reg         buy_sell,
    output reg [31:0]  shares,
    output reg [31:0]  price,
    output reg [63:0]  stock_symbol
);

// Internal parsing
wire [7:0] msg_type;
assign msg_type = payload[511:504];

always @(posedge clk or negedge rst_n) begin
    if (!rst_n) begin
        add_order_decoded <= 1'b0;
        order_ref <= 64'd0;
        buy_sell <= 1'b0;
        shares <= 32'd0;
        price <= 32'd0;
        stock_symbol <= 64'd0;
    end else if (valid) begin
        if (msg_type == "A") begin
            add_order_decoded <= 1'b1;
            order_ref <= payload[503:440];
            buy_sell <= (payload[439:432] == "B") ? 1'b1 : 1'b0; // 1=Buy, 0=Sell
            shares <= payload[431:400];
            stock_symbol <= payload[399:336];
            price <= payload[335:304];
        end else begin
            add_order_decoded <= 1'b0;
        end
    end else begin
        add_order_decoded <= 1'b0;
    end
end

endmodule

payload_parser_standalone/rtl/payload_dispatcher.v
// =============================================
// payload_dispatcher.v
// =============================================
//
// Description: Dispatcher module to route ITCH payloads based on message type.
// Author: RZ
// Start Date: 04172025
// Version: 0.1
//
// Changelog
// =============================================
// [20250427-1] RZ: Initial version supporting Add Order ('A') and Cancel Order ('X') dispatching.
// [20250428-1] RZ: Added Delete Order ('D') message dispatching.
// =============================================

`timescale 1ns/1ps

module payload_dispatcher (
    input  wire        clk,
    input  wire        rst_n,
    input  wire        in_valid,
    input  wire [7:0]  msg_type,
    input  wire [511:0] payload,

    output wire        add_order_decoded,
    output wire [63:0] order_ref,
    output wire        buy_sell,
    output wire [31:0] shares,
    output wire [31:0] price,
    output wire [63:0] stock_symbol,

    output wire        cancel_order_decoded,
    output wire [63:0] cancel_order_ref,
    output wire [31:0] cancel_shares,

    output wire        delete_order_decoded,
    output wire [63:0] delete_order_ref,

    output wire        replace_order_decoded,
    output wire [63:0] original_ref,
    output wire [63:0] new_ref,
    output wire [31:0] shares_replace

);

// Submodule instances
add_order_decoder u_add_order_decoder (
    .clk(clk),
    .rst_n(rst_n),
    .valid(in_valid && (msg_type == "A")),
    .payload(payload),
    .add_order_decoded(add_order_decoded),
    .order_ref(order_ref),
    .buy_sell(buy_sell),
    .shares(shares),
    .price(price),
    .stock_symbol(stock_symbol)
);

cancel_order_decoder u_cancel_order_decoder (
    .clk(clk),
    .rst_n(rst_n),
    .valid(in_valid && (msg_type == "X")),
    .payload(payload),
    .cancel_order_decoded(cancel_order_decoded),
    .cancel_order_ref(cancel_order_ref),
    .cancel_shares(cancel_shares)
);

delete_order_decoder u_delete_order_decoder (
    .clk(clk),
    .rst_n(rst_n),
    .valid(in_valid && (msg_type == "D")),
    .payload(payload),
    .delete_order_decoded(delete_order_decoded),
    .delete_order_ref(delete_order_ref)
);

replace_order_decoder u_replace_order_decoder (
    .clk(clk),
    .rst_n(rst_n),
    .valid(in_valid && (msg_type == "U")),
    .payload(payload),
    .replace_order_decoded(replace_order_decoded),
    .original_ref(original_ref),
    .new_ref(new_ref),
    .shares(shares)
);


endmodule

payload_parser_standalone/synth/top.v
// =============================================
// top.v
// =============================================
//
// Description: Top-level wrapper for cocotb simulation, handles VCD dumping.
// Author: RZ
// Start Date: 04172025
// Version: 0.1
//
// Changelog
// =============================================
// [20250427-1] RZ: Updated VCD dumping to allow dynamic filename selection via DUMPFILE macro.
// [20250428-1] RZ: Standardized dumpfile to "dump.vcd" for all simulation targets.
// [20250428-2] RZ: Updated dispatcher instantiation to match new decoded signal structure.
// [20250428-3] RZ: Added Replace Order decoder instantiation and connections.
// [20250428-4] RZ: Fixed syntax errors in module instantiation and signal connections.
// =============================================

`timescale 1ns/1ps

module top (
    input  wire        clk,
    input  wire        rst_n,

    input  wire        in_valid,
    input  wire [7:0]  msg_type,
    input  wire [511:0] payload,

    output wire        add_order_decoded,
    output wire [63:0] order_ref,
    output wire        buy_sell,
    output wire [31:0] add_order_shares,
    output wire [31:0] price,
    output wire [63:0] stock_symbol,

    output wire        cancel_order_decoded,
    output wire [63:0] cancel_order_ref,
    output wire [31:0] cancel_shares,

    output wire        delete_order_decoded,
    output wire [63:0] delete_order_ref,

    output wire        replace_order_decoded,
    output wire [63:0] original_ref,
    output wire [63:0] new_ref,
    output wire [31:0] replace_order_shares
);

payload_dispatcher dispatcher_inst (
    .clk(clk),
    .rst_n(rst_n),
    .in_valid(in_valid),
    .msg_type(msg_type),
    .payload(payload),

    .add_order_decoded(add_order_decoded),
    .order_ref(order_ref),
    .buy_sell(buy_sell),
    .shares(add_order_shares),
    .price(price),
    .stock_symbol(stock_symbol),

    .cancel_order_decoded(cancel_order_decoded),
    .cancel_order_ref(cancel_order_ref),
    .cancel_shares(cancel_shares),

    .delete_order_decoded(delete_order_decoded),
    .delete_order_ref(delete_order_ref),

    .replace_order_decoded(replace_order_decoded),
    .original_ref(original_ref),
    .new_ref(new_ref),
    .shares_replace(replace_order_shares)
);

`ifdef COCOTB_SIM
initial begin
    $dumpfile("dump.vcd");
    $dumpvars(0, top);
end
`endif

endmodule

payload_parser_standalone/sim/vcd/full_test_dump_04282025_213019.vcd
$date
	Mon Apr 28 21:30:19 2025
$end
$version
	Icarus Verilog
$end
$timescale
	1ps
$end
$scope module top $end
$var wire 32 ! add_order_shares [31:0] $end
$var wire 1 " clk $end
$var wire 1 # in_valid $end
$var wire 8 $ msg_type [7:0] $end
$var wire 512 % payload [511:0] $end
$var wire 32 & replace_order_shares [31:0] $end
$var wire 1 ' rst_n $end
$var wire 64 ( stock_symbol [63:0] $end
$var wire 1 ) replace_order_decoded $end
$var wire 32 * price [31:0] $end
$var wire 64 + original_ref [63:0] $end
$var wire 64 , order_ref [63:0] $end
$var wire 64 - new_ref [63:0] $end
$var wire 64 . delete_order_ref [63:0] $end
$var wire 1 / delete_order_decoded $end
$var wire 32 0 cancel_shares [31:0] $end
$var wire 64 1 cancel_order_ref [63:0] $end
$var wire 1 2 cancel_order_decoded $end
$var wire 1 3 buy_sell $end
$var wire 1 4 add_order_decoded $end
$scope module dispatcher_inst $end
$var wire 1 " clk $end
$var wire 1 # in_valid $end
$var wire 8 5 msg_type [7:0] $end
$var wire 512 6 payload [511:0] $end
$var wire 1 ' rst_n $end
$var wire 32 7 shares [31:0] $end
$var wire 32 8 shares_replace [31:0] $end
$var wire 64 9 stock_symbol [63:0] $end
$var wire 1 ) replace_order_decoded $end
$var wire 32 : price [31:0] $end
$var wire 64 ; original_ref [63:0] $end
$var wire 64 < order_ref [63:0] $end
$var wire 64 = new_ref [63:0] $end
$var wire 64 > delete_order_ref [63:0] $end
$var wire 1 / delete_order_decoded $end
$var wire 32 ? cancel_shares [31:0] $end
$var wire 64 @ cancel_order_ref [63:0] $end
$var wire 1 2 cancel_order_decoded $end
$var wire 1 3 buy_sell $end
$var wire 1 4 add_order_decoded $end
$scope module u_add_order_decoder $end
$var wire 1 " clk $end
$var wire 512 A payload [511:0] $end
$var wire 1 ' rst_n $end
$var wire 1 B valid $end
$var wire 8 C msg_type [7:0] $end
$var reg 1 4 add_order_decoded $end
$var reg 1 3 buy_sell $end
$var reg 64 D order_ref [63:0] $end
$var reg 32 E price [31:0] $end
$var reg 32 F shares [31:0] $end
$var reg 64 G stock_symbol [63:0] $end
$upscope $end
$scope module u_cancel_order_decoder $end
$var wire 1 " clk $end
$var wire 512 H payload [511:0] $end
$var wire 1 ' rst_n $end
$var wire 1 I valid $end
$var wire 8 J msg_type [7:0] $end
$var reg 1 2 cancel_order_decoded $end
$var reg 64 K cancel_order_ref [63:0] $end
$var reg 32 L cancel_shares [31:0] $end
$upscope $end
$scope module u_delete_order_decoder $end
$var wire 1 " clk $end
$var wire 512 M payload [511:0] $end
$var wire 1 ' rst_n $end
$var wire 1 N valid $end
$var wire 64 O order_ref [63:0] $end
$var wire 8 P msg_type [7:0] $end
$var reg 1 / delete_order_decoded $end
$var reg 64 Q delete_order_ref [63:0] $end
$upscope $end
$scope module u_replace_order_decoder $end
$var wire 1 " clk $end
$var wire 512 R payload [511:0] $end
$var wire 1 ' rst_n $end
$var wire 1 S valid $end
$var wire 8 T msg_type [7:0] $end
$var reg 64 U new_ref [63:0] $end
$var reg 64 V original_ref [63:0] $end
$var reg 1 ) replace_order_decoded $end
$var reg 32 W shares [31:0] $end
$upscope $end
$upscope $end
$upscope $end
$enddefinitions $end
#0
$dumpvars
b0 W
b0 V
b0 U
bz T
xS
bz R
b0 Q
bz P
bz O
xN
bz M
b0 L
b0 K
bz J
xI
bz H
b0 G
b0 F
b0 E
b0 D
bz C
xB
bz A
b0 @
b0 ?
b0 >
b0 =
b0 <
b0 ;
b0 :
b0 9
bz 8
b0 7
bz 6
bz 5
04
03
02
b0 1
b0 0
0/
b0 .
b0 -
b0 ,
b0 +
b0 *
0)
b0 (
0'
bz &
bz %
bz $
z#
1"
b0 !
$end
#5000
0"
#10000
1'
1"
#15000
0"
#20000
b1000001 C
b1000001 J
b1000001 P
b1001000110100010101100111100000000000000000000000000000000000 O
b1000001 T
1B
0I
0N
0S
b1000001000100100011010001010110011110000000000000000000000000000000000001000010000000000000000000000011111010000100011101001111010011110100011100100000001000000010000000100000000000000000000110000110101000000000000000000000000000000000000000000000000000000000000000000000000000000000000000000000000000000000000000000000000000000000000000000000000000000000000000000000000000000000000000000000000000000000000000000000000000000000000000000000000000000000000000000000000000000000000000000000000000000000000000000000 %
b1000001000100100011010001010110011110000000000000000000000000000000000001000010000000000000000000000011111010000100011101001111010011110100011100100000001000000010000000100000000000000000000110000110101000000000000000000000000000000000000000000000000000000000000000000000000000000000000000000000000000000000000000000000000000000000000000000000000000000000000000000000000000000000000000000000000000000000000000000000000000000000000000000000000000000000000000000000000000000000000000000000000000000000000000000000 6
b1000001000100100011010001010110011110000000000000000000000000000000000001000010000000000000000000000011111010000100011101001111010011110100011100100000001000000010000000100000000000000000000110000110101000000000000000000000000000000000000000000000000000000000000000000000000000000000000000000000000000000000000000000000000000000000000000000000000000000000000000000000000000000000000000000000000000000000000000000000000000000000000000000000000000000000000000000000000000000000000000000000000000000000000000000000 A
b1000001000100100011010001010110011110000000000000000000000000000000000001000010000000000000000000000011111010000100011101001111010011110100011100100000001000000010000000100000000000000000000110000110101000000000000000000000000000000000000000000000000000000000000000000000000000000000000000000000000000000000000000000000000000000000000000000000000000000000000000000000000000000000000000000000000000000000000000000000000000000000000000000000000000000000000000000000000000000000000000000000000000000000000000000000 H
b1000001000100100011010001010110011110000000000000000000000000000000000001000010000000000000000000000011111010000100011101001111010011110100011100100000001000000010000000100000000000000000000110000110101000000000000000000000000000000000000000000000000000000000000000000000000000000000000000000000000000000000000000000000000000000000000000000000000000000000000000000000000000000000000000000000000000000000000000000000000000000000000000000000000000000000000000000000000000000000000000000000000000000000000000000000 M
b1000001000100100011010001010110011110000000000000000000000000000000000001000010000000000000000000000011111010000100011101001111010011110100011100100000001000000010000000100000000000000000000110000110101000000000000000000000000000000000000000000000000000000000000000000000000000000000000000000000000000000000000000000000000000000000000000000000000000000000000000000000000000000000000000000000000000000000000000000000000000000000000000000000000000000000000000000000000000000000000000000000000000000000000000000000 R
b1000001 $
b1000001 5
1#
1"
#25000
0"
#30000
0B
0#
b11000011010100000 *
b11000011010100000 :
b11000011010100000 E
b100011101001111010011110100011100100000001000000010000000100000 (
b100011101001111010011110100011100100000001000000010000000100000 9
b100011101001111010011110100011100100000001000000010000000100000 G
b0xxxxx0x000 !
b0xxxxx0x000 7
b1111101000 F
13
b1001000110100010101100111100000000000000000000000000000000000 ,
b1001000110100010101100111100000000000000000000000000000000000 <
b1001000110100010101100111100000000000000000000000000000000000 D
14
1"
#35000
0"
#40000
04
1"
#45000
0"
#50000
1"
#55000
0"
#60000
1"
#65000
0"
#70000
1"
#75000
0"
#80000
b1011111 C
b1011111 J
b1011111 P
b11111010111010001101010100100101010111110100011110100001011010 O
b1011111 T
b1011111001111101011101000110101010010010101011111010001111010000101101001111001101011010001111101011001010100000110110001010110001111001100101110100100101101001110111000100110111011010000000010110111111101110000110011001000001011100101001110101001001110110100100110111110111111000111101011000001001000110000111101011000100111000101001010110001010101001100010010110110000101111111010000111111010011100111010011011111010011111110000101110101101011100001110111100100110001001001011101111100010011001011110110100011 %
b1011111001111101011101000110101010010010101011111010001111010000101101001111001101011010001111101011001010100000110110001010110001111001100101110100100101101001110111000100110111011010000000010110111111101110000110011001000001011100101001110101001001110110100100110111110111111000111101011000001001000110000111101011000100111000101001010110001010101001100010010110110000101111111010000111111010011100111010011011111010011111110000101110101101011100001110111100100110001001001011101111100010011001011110110100011 6
b1011111001111101011101000110101010010010101011111010001111010000101101001111001101011010001111101011001010100000110110001010110001111001100101110100100101101001110111000100110111011010000000010110111111101110000110011001000001011100101001110101001001110110100100110111110111111000111101011000001001000110000111101011000100111000101001010110001010101001100010010110110000101111111010000111111010011100111010011011111010011111110000101110101101011100001110111100100110001001001011101111100010011001011110110100011 A
b1011111001111101011101000110101010010010101011111010001111010000101101001111001101011010001111101011001010100000110110001010110001111001100101110100100101101001110111000100110111011010000000010110111111101110000110011001000001011100101001110101001001110110100100110111110111111000111101011000001001000110000111101011000100111000101001010110001010101001100010010110110000101111111010000111111010011100111010011011111010011111110000101110101101011100001110111100100110001001001011101111100010011001011110110100011 H
b1011111001111101011101000110101010010010101011111010001111010000101101001111001101011010001111101011001010100000110110001010110001111001100101110100100101101001110111000100110111011010000000010110111111101110000110011001000001011100101001110101001001110110100100110111110111111000111101011000001001000110000111101011000100111000101001010110001010101001100010010110110000101111111010000111111010011100111010011011111010011111110000101110101101011100001110111100100110001001001011101111100010011001011110110100011 M
b1011111001111101011101000110101010010010101011111010001111010000101101001111001101011010001111101011001010100000110110001010110001111001100101110100100101101001110111000100110111011010000000010110111111101110000110011001000001011100101001110101001001110110100100110111110111111000111101011000001001000110000111101011000100111000101001010110001010101001100010010110110000101111111010000111111010011100111010011011111010011111110000101110101101011100001110111100100110001001001011101111100010011001011110110100011 R
b100101 $
b100101 5
1#
1"
#85000
0"
#90000
0#
1"
#95000
0"
#100000
b1000001 C
b1000001 J
b1000001 P
b0 O
b1000001 T
1B
b1000001000000000000000000000000000000000000000000000000000000000000000000000000000000000000000000000000000000000000000000000000000000000000000000000000000000000000000000000000000000000000000000000000000000000000000000000000000000000000000000000000000000000000000000000000000000000000000000000000000000000000000000000000000000000000000000000000000000000000000000000000000000000000000000000000000000000000000000000000000000000000000000000000000000000000000000000000000000000000000000000000000000000000000000000000 %
b1000001000000000000000000000000000000000000000000000000000000000000000000000000000000000000000000000000000000000000000000000000000000000000000000000000000000000000000000000000000000000000000000000000000000000000000000000000000000000000000000000000000000000000000000000000000000000000000000000000000000000000000000000000000000000000000000000000000000000000000000000000000000000000000000000000000000000000000000000000000000000000000000000000000000000000000000000000000000000000000000000000000000000000000000000000 6
b1000001000000000000000000000000000000000000000000000000000000000000000000000000000000000000000000000000000000000000000000000000000000000000000000000000000000000000000000000000000000000000000000000000000000000000000000000000000000000000000000000000000000000000000000000000000000000000000000000000000000000000000000000000000000000000000000000000000000000000000000000000000000000000000000000000000000000000000000000000000000000000000000000000000000000000000000000000000000000000000000000000000000000000000000000000 A
b1000001000000000000000000000000000000000000000000000000000000000000000000000000000000000000000000000000000000000000000000000000000000000000000000000000000000000000000000000000000000000000000000000000000000000000000000000000000000000000000000000000000000000000000000000000000000000000000000000000000000000000000000000000000000000000000000000000000000000000000000000000000000000000000000000000000000000000000000000000000000000000000000000000000000000000000000000000000000000000000000000000000000000000000000000000 H
b1000001000000000000000000000000000000000000000000000000000000000000000000000000000000000000000000000000000000000000000000000000000000000000000000000000000000000000000000000000000000000000000000000000000000000000000000000000000000000000000000000000000000000000000000000000000000000000000000000000000000000000000000000000000000000000000000000000000000000000000000000000000000000000000000000000000000000000000000000000000000000000000000000000000000000000000000000000000000000000000000000000000000000000000000000000 M
b1000001000000000000000000000000000000000000000000000000000000000000000000000000000000000000000000000000000000000000000000000000000000000000000000000000000000000000000000000000000000000000000000000000000000000000000000000000000000000000000000000000000000000000000000000000000000000000000000000000000000000000000000000000000000000000000000000000000000000000000000000000000000000000000000000000000000000000000000000000000000000000000000000000000000000000000000000000000000000000000000000000000000000000000000000000 R
b1000001 $
b1000001 5
1#
1"
#105000
0"
#110000
0B
0#
b0 *
b0 :
b0 E
b0 (
b0 9
b0 G
b0 !
b0 7
b0 F
03
b0 ,
b0 <
b0 D
14
1"
#115000
0"
#120000
04
1"
