payload_parser_standalone/rtl/cancel_order_decoder.v
module cancel_order_decoder (
    input  wire        clk,
    input  wire        rst_n,

    input  wire        valid,
    input  wire [511:0] payload,

    output reg  [63:0] order_ref,
    output reg  [31:0] cancel_shares,
    output reg         decoded
);

    always @(posedge clk or negedge rst_n) begin
        if (!rst_n) begin
            order_ref     <= 64'd0;
            cancel_shares <= 32'd0;
            decoded       <= 1'b0;
        end else begin
            decoded <= 1'b0;
            if (valid) begin
                order_ref     <= payload[511-8*1  -: 64]; // bytes 1-8: order reference
                cancel_shares <= payload[511-8*9  -: 32]; // bytes 9-12: cancel shares
                decoded       <= 1'b1;
            end
        end
    end

endmodule

payload_parser_standalone/rtl/add_order_decoder.v
// =============================================
// add_order_decoder.v
// =============================================
//
// Description: Module to decode Add Order ('A') messages from ITCH payloads.
// Author: RZ
// Start Date: 04172025
// Version: 0.1
//
// Changelog
// =============================================
// [20250427-1] RZ: Initial version created for Add Order payload decoding.
// [20250428-1] RZ: Added stock symbol extraction and minor optimizations.
// =============================================

module add_order_decoder (
    input  wire        clk,
    input  wire        rst_n,

    input  wire        valid,
    input  wire [511:0] payload,

    output reg  [63:0] order_ref,
    output reg         buy_sell,
    output reg  [31:0] shares,
    output reg  [31:0] price,
    output reg  [63:0] stock_symbol,
    output reg         decoded
);

    always @(posedge clk or negedge rst_n) begin
        if (!rst_n) begin
            order_ref     <= 0;
            buy_sell      <= 0;
            shares        <= 0;
            price         <= 0;
            stock_symbol  <= 0;
            decoded       <= 0;
        end else begin
            decoded <= 0;
            if (valid) begin
                order_ref     <= payload[511-8*1  -: 64];   // 1–8
                buy_sell      <= (payload[511-8*9  -: 8] == "S") ? 1'b1 : 1'b0; // 9
                shares        <= payload[511-8*10 -: 32];   // 10–13
                stock_symbol  <= payload[511-8*14 -: 64];   // 14–21
                price         <= payload[511-8*22 -: 32];   // 22–25
                decoded       <= 1'b1;
            end
        end
    end

endmodule

payload_parser_standalone/rtl/payload_dispatcher.v
// =============================================
// Changelog
// =============================================
// [04272025] RZ: Initial version for payload dispatcher.
//              Supports Add Order ('A') and Cancel Order ('X') dispatching. 
// =============================================

// ===============================
// payload_dispatcher.v
// ===============================

module payload_dispatcher #(
    parameter PAYLOAD_WIDTH = 512
)(
    input  wire        clk,
    input  wire        rst_n,

    input  wire        in_valid,
    input  wire [7:0]  msg_type,
    input  wire [PAYLOAD_WIDTH-1:0] payload,

    output reg         add_order_valid,
    output reg [PAYLOAD_WIDTH-1:0] add_order_payload,

    output reg         cancel_order_valid,
    output reg [PAYLOAD_WIDTH-1:0] cancel_order_payload
);

    always @(posedge clk or negedge rst_n) begin
        if (!rst_n) begin
            add_order_valid     <= 1'b0;
            add_order_payload   <= {PAYLOAD_WIDTH{1'b0}};
            cancel_order_valid  <= 1'b0;
            cancel_order_payload<= {PAYLOAD_WIDTH{1'b0}};
        end else begin
            add_order_valid     <= 1'b0;
            add_order_payload   <= {PAYLOAD_WIDTH{1'b0}};
            cancel_order_valid  <= 1'b0;
            cancel_order_payload<= {PAYLOAD_WIDTH{1'b0}};
            if (in_valid) begin
                if (msg_type == 8'h41) begin // 'A' Add Order
                    add_order_valid   <= 1'b1;
                    add_order_payload <= payload;
                end else if (msg_type == 8'h58) begin // 'X' Cancel Order
                    cancel_order_valid   <= 1'b1;
                    cancel_order_payload <= payload;
                end
            end
        end
    end

endmodule

payload_parser_standalone/synth/top.v

// Changelog
// =============================================

// [04272025] RZ: Updated VCD dumping to allow dynamic filename selection via DUMPFILE macro.
//              Made this change to make debugging different modules easier
//==============================================

// ===============================
// top.v
// ===============================
`timescale 1ns/1ps



module top (
    input  wire        clk,
    input  wire        rst_n,

    input  wire        in_valid,
    input  wire [7:0]  msg_type,
    input  wire [511:0] payload,

    output wire        add_order_decoded,
    output wire [63:0] order_ref,
    output wire        buy_sell,
    output wire [31:0] shares,
    output wire [31:0] price,
    output wire [63:0] stock_symbol,

    output wire        cancel_order_decoded,
    output wire [63:0] cancel_order_ref,
    output wire [31:0] cancel_shares
);

    wire        add_order_valid;
    wire [511:0] add_order_payload;

    wire        cancel_order_valid;
    wire [511:0] cancel_order_payload;

    payload_dispatcher dispatcher_inst (
        .clk(clk),
        .rst_n(rst_n),
        .in_valid(in_valid),
        .msg_type(msg_type),
        .payload(payload),
        .add_order_valid(add_order_valid),
        .add_order_payload(add_order_payload),
        .cancel_order_valid(cancel_order_valid),
        .cancel_order_payload(cancel_order_payload)
    );

    add_order_decoder add_order_decoder_inst (
        .clk(clk),
        .rst_n(rst_n),
        .valid(add_order_valid),
        .payload(add_order_payload),
        .order_ref(order_ref),
        .buy_sell(buy_sell),
        .shares(shares),
        .price(price),
        .stock_symbol(stock_symbol),
        .decoded(add_order_decoded)
    );

    cancel_order_decoder cancel_order_decoder_inst (
        .clk(clk),
        .rst_n(rst_n),
        .valid(cancel_order_valid),
        .payload(cancel_order_payload),
        .order_ref(cancel_order_ref),
        .cancel_shares(cancel_shares),
        .decoded(cancel_order_decoded)
    );

`ifdef COCOTB_SIM
    `ifdef DUMPFILE
        `define DUMPFILE_STRING `DUMPFILE
    `else
        `define DUMPFILE_STRING "default_dump.vcd"
    `endif

    initial begin
        $dumpfile(`DUMPFILE_STRING);
        $dumpvars(0, top);
    end
`endif




endmodule

payload_parser_standalone/sim/add_order_dump_04272025_221744.vcd
$date
	Sun Apr 27 22:32:14 2025
$end
$version
	Icarus Verilog
$end
$timescale
	1ps
$end
$scope module top $end
$var wire 1 ! clk $end
$var wire 1 " in_valid $end
$var wire 8 # msg_type [7:0] $end
$var wire 512 $ payload [511:0] $end
$var wire 1 % rst_n $end
$var wire 64 & stock_symbol [63:0] $end
$var wire 32 ' shares [31:0] $end
$var wire 32 ( price [31:0] $end
$var wire 64 ) order_ref [63:0] $end
$var wire 32 * cancel_shares [31:0] $end
$var wire 1 + cancel_order_valid $end
$var wire 64 , cancel_order_ref [63:0] $end
$var wire 512 - cancel_order_payload [511:0] $end
$var wire 1 . cancel_order_decoded $end
$var wire 1 / buy_sell $end
$var wire 1 0 add_order_valid $end
$var wire 512 1 add_order_payload [511:0] $end
$var wire 1 2 add_order_decoded $end
$scope module add_order_decoder_inst $end
$var wire 1 ! clk $end
$var wire 1 % rst_n $end
$var wire 1 0 valid $end
$var wire 512 3 payload [511:0] $end
$var reg 1 / buy_sell $end
$var reg 1 2 decoded $end
$var reg 64 4 order_ref [63:0] $end
$var reg 32 5 price [31:0] $end
$var reg 32 6 shares [31:0] $end
$var reg 64 7 stock_symbol [63:0] $end
$upscope $end
$scope module cancel_order_decoder_inst $end
$var wire 1 ! clk $end
$var wire 1 % rst_n $end
$var wire 1 + valid $end
$var wire 512 8 payload [511:0] $end
$var reg 32 9 cancel_shares [31:0] $end
$var reg 1 . decoded $end
$var reg 64 : order_ref [63:0] $end
$upscope $end
$scope module dispatcher_inst $end
$var wire 1 ! clk $end
$var wire 1 " in_valid $end
$var wire 8 ; msg_type [7:0] $end
$var wire 512 < payload [511:0] $end
$var wire 1 % rst_n $end
$var reg 512 = add_order_payload [511:0] $end
$var reg 1 0 add_order_valid $end
$var reg 512 > cancel_order_payload [511:0] $end
$var reg 1 + cancel_order_valid $end
$upscope $end
$upscope $end
$enddefinitions $end
#0
$dumpvars
b0 >
b0 =
bz <
bz ;
b0 :
b0 9
b0 8
b0 7
b0 6
b0 5
b0 4
b0 3
02
b0 1
00
0/
0.
b0 -
b0 ,
0+
b0 *
b0 )
b0 (
b0 '
b0 &
0%
bz $
bz #
z"
1!
$end
#5000
0!
#10000
1%
1!
#15000
0!
#20000
0%
1!
#25000
0!
#30000
1!
#35000
0!
#40000
1%
1!
#45000
0!
#50000
b100100111000001110001000011111001010111110111111000000100010011010101000100000111100010111100010010000101110010010011110101110111111001010101100110001011101010101101000111010110101011110111011100110111011011110101101110111000101101011111110101100100010000110011000000111100000100100110111111101111000000101000111101000111001111011110110001111001001110001001111111100000001110111000010111101101110001001000111000011101111000000111111010000100110010111101110110101101111001110000111011110110100010010111011101110 $
b100100111000001110001000011111001010111110111111000000100010011010101000100000111100010111100010010000101110010010011110101110111111001010101100110001011101010101101000111010110101011110111011100110111011011110101101110111000101101011111110101100100010000110011000000111100000100100110111111101111000000101000111101000111001111011110110001111001001110001001111111100000001110111000010111101101110001001000111000011101111000000111111010000100110010111101110110101101111001110000111011110110100010010111011101110 <
b1001110 #
b1001110 ;
1"
1!
#55000
0!
#60000
0"
1!
#65000
0!
#70000
b1000001000000000000000000000000000000000000000000000000000000000000000000000000000000000000000000000000000000000000000000000000000000000000000000000000000000000000000000000000000000000000000000000000000000000000000000000000000000000000000000000000000000000000000000000000000000000000000000000000000000000000000000000000000000000000000000000000000000000000000000000000000000000000000000000000000000000000000000000000000000000000000000000000000000000000000000000000000000000000000000000000000000000000000000000000 $
b1000001000000000000000000000000000000000000000000000000000000000000000000000000000000000000000000000000000000000000000000000000000000000000000000000000000000000000000000000000000000000000000000000000000000000000000000000000000000000000000000000000000000000000000000000000000000000000000000000000000000000000000000000000000000000000000000000000000000000000000000000000000000000000000000000000000000000000000000000000000000000000000000000000000000000000000000000000000000000000000000000000000000000000000000000000 <
b1000001 #
b1000001 ;
1"
1!
#75000
0!
#80000
0"
b1000001000000000000000000000000000000000000000000000000000000000000000000000000000000000000000000000000000000000000000000000000000000000000000000000000000000000000000000000000000000000000000000000000000000000000000000000000000000000000000000000000000000000000000000000000000000000000000000000000000000000000000000000000000000000000000000000000000000000000000000000000000000000000000000000000000000000000000000000000000000000000000000000000000000000000000000000000000000000000000000000000000000000000000000000000 1
b1000001000000000000000000000000000000000000000000000000000000000000000000000000000000000000000000000000000000000000000000000000000000000000000000000000000000000000000000000000000000000000000000000000000000000000000000000000000000000000000000000000000000000000000000000000000000000000000000000000000000000000000000000000000000000000000000000000000000000000000000000000000000000000000000000000000000000000000000000000000000000000000000000000000000000000000000000000000000000000000000000000000000000000000000000000 3
b1000001000000000000000000000000000000000000000000000000000000000000000000000000000000000000000000000000000000000000000000000000000000000000000000000000000000000000000000000000000000000000000000000000000000000000000000000000000000000000000000000000000000000000000000000000000000000000000000000000000000000000000000000000000000000000000000000000000000000000000000000000000000000000000000000000000000000000000000000000000000000000000000000000000000000000000000000000000000000000000000000000000000000000000000000000 =
10
1!
#85000
0!
#90000
b1011010000000000000000000000000000000000000000000000000000000000000000000000000000000000000000000000000000000000000000000000000000000000000000000000000000000000000000000000000000000000000000000000000000000000000000000000000000000000000000000000000000000000000000000000000000000000000000000000000000000000000000000000000000000000000000000000000000000000000000000000000000000000000000000000000000000000000000000000000000000000000000000000000000000000000000000000000000000000000000000000000000000000000000000000000 $
b1011010000000000000000000000000000000000000000000000000000000000000000000000000000000000000000000000000000000000000000000000000000000000000000000000000000000000000000000000000000000000000000000000000000000000000000000000000000000000000000000000000000000000000000000000000000000000000000000000000000000000000000000000000000000000000000000000000000000000000000000000000000000000000000000000000000000000000000000000000000000000000000000000000000000000000000000000000000000000000000000000000000000000000000000000000 <
b1011010 #
b1011010 ;
1"
b0 1
b0 3
b0 =
00
12
1!
#95000
0!
#100000
0"
02
1!
#105000
0!
#110000
b1000001000100100011010001010110011110000000000000000000000000000000000001000010000000000000000000000011111010000100011101001111010011110100011100100000001000000010000000100000000000000000000110000110101000000000000000000000000000000000000000000000000000000000000000000000000000000000000000000000000000000000000000000000000000000000000000000000000000000000000000000000000000000000000000000000000000000000000000000000000000000000000000000000000000000000000000000000000000000000000000000000000000000000000000000000 $
b1000001000100100011010001010110011110000000000000000000000000000000000001000010000000000000000000000011111010000100011101001111010011110100011100100000001000000010000000100000000000000000000110000110101000000000000000000000000000000000000000000000000000000000000000000000000000000000000000000000000000000000000000000000000000000000000000000000000000000000000000000000000000000000000000000000000000000000000000000000000000000000000000000000000000000000000000000000000000000000000000000000000000000000000000000000 <
b1000001 #
b1000001 ;
1"
1!
#115000
0!
#120000
0"
b1000001000100100011010001010110011110000000000000000000000000000000000001000010000000000000000000000011111010000100011101001111010011110100011100100000001000000010000000100000000000000000000110000110101000000000000000000000000000000000000000000000000000000000000000000000000000000000000000000000000000000000000000000000000000000000000000000000000000000000000000000000000000000000000000000000000000000000000000000000000000000000000000000000000000000000000000000000000000000000000000000000000000000000000000000000 1
b1000001000100100011010001010110011110000000000000000000000000000000000001000010000000000000000000000011111010000100011101001111010011110100011100100000001000000010000000100000000000000000000110000110101000000000000000000000000000000000000000000000000000000000000000000000000000000000000000000000000000000000000000000000000000000000000000000000000000000000000000000000000000000000000000000000000000000000000000000000000000000000000000000000000000000000000000000000000000000000000000000000000000000000000000000000 3
b1000001000100100011010001010110011110000000000000000000000000000000000001000010000000000000000000000011111010000100011101001111010011110100011100100000001000000010000000100000000000000000000110000110101000000000000000000000000000000000000000000000000000000000000000000000000000000000000000000000000000000000000000000000000000000000000000000000000000000000000000000000000000000000000000000000000000000000000000000000000000000000000000000000000000000000000000000000000000000000000000000000000000000000000000000000 =
10
1!
#125000
0!
#130000
b0 1
b0 3
b0 =
00
12
b11000011010100000 (
b11000011010100000 5
b100011101001111010011110100011100100000001000000010000000100000 &
b100011101001111010011110100011100100000001000000010000000100000 7
b1111101000 '
b1111101000 6
b1001000110100010101100111100000000000000000000000000000000000 )
b1001000110100010101100111100000000000000000000000000000000000 4
1!
#135000
0!
#140000
b1000001000100100011010001010110011110000000000000000000000000000000000101000010000000000000000000000011111010010100011101001111010011110100011100100000001000000010000000100000000000000000000110000110101010100000000000000000000000000000000000000000000000000000000000000000000000000000000000000000000000000000000000000000000000000000000000000000000000000000000000000000000000000000000000000000000000000000000000000000000000000000000000000000000000000000000000000000000000000000000000000000000000000000000000000000 $
b1000001000100100011010001010110011110000000000000000000000000000000000101000010000000000000000000000011111010010100011101001111010011110100011100100000001000000010000000100000000000000000000110000110101010100000000000000000000000000000000000000000000000000000000000000000000000000000000000000000000000000000000000000000000000000000000000000000000000000000000000000000000000000000000000000000000000000000000000000000000000000000000000000000000000000000000000000000000000000000000000000000000000000000000000000000 <
1"
02
1!
#145000
0!
#150000
0"
b1000001000100100011010001010110011110000000000000000000000000000000000101000010000000000000000000000011111010010100011101001111010011110100011100100000001000000010000000100000000000000000000110000110101010100000000000000000000000000000000000000000000000000000000000000000000000000000000000000000000000000000000000000000000000000000000000000000000000000000000000000000000000000000000000000000000000000000000000000000000000000000000000000000000000000000000000000000000000000000000000000000000000000000000000000000 1
b1000001000100100011010001010110011110000000000000000000000000000000000101000010000000000000000000000011111010010100011101001111010011110100011100100000001000000010000000100000000000000000000110000110101010100000000000000000000000000000000000000000000000000000000000000000000000000000000000000000000000000000000000000000000000000000000000000000000000000000000000000000000000000000000000000000000000000000000000000000000000000000000000000000000000000000000000000000000000000000000000000000000000000000000000000000 3
b1000001000100100011010001010110011110000000000000000000000000000000000101000010000000000000000000000011111010010100011101001111010011110100011100100000001000000010000000100000000000000000000110000110101010100000000000000000000000000000000000000000000000000000000000000000000000000000000000000000000000000000000000000000000000000000000000000000000000000000000000000000000000000000000000000000000000000000000000000000000000000000000000000000000000000000000000000000000000000000000000000000000000000000000000000000 =
10
1!
#155000
0!
#160000
12
b11000011010101010 (
b11000011010101010 5
b1111101001 '
b1111101001 6
b1001000110100010101100111100000000000000000000000000000000001 )
b1001000110100010101100111100000000000000000000000000000000001 4
b0 1
b0 3
b0 =
00
1!
#165000
0!
#170000
b1000001000100100011010001010110011110000000000000000000000000000000001001000010000000000000000000000011111010100100011101001111010011110100011100100000001000000010000000100000000000000000000110000110101101000000000000000000000000000000000000000000000000000000000000000000000000000000000000000000000000000000000000000000000000000000000000000000000000000000000000000000000000000000000000000000000000000000000000000000000000000000000000000000000000000000000000000000000000000000000000000000000000000000000000000000 $
b1000001000100100011010001010110011110000000000000000000000000000000001001000010000000000000000000000011111010100100011101001111010011110100011100100000001000000010000000100000000000000000000110000110101101000000000000000000000000000000000000000000000000000000000000000000000000000000000000000000000000000000000000000000000000000000000000000000000000000000000000000000000000000000000000000000000000000000000000000000000000000000000000000000000000000000000000000000000000000000000000000000000000000000000000000000 <
1"
02
1!
#175000
0!
#180000
0"
b1000001000100100011010001010110011110000000000000000000000000000000001001000010000000000000000000000011111010100100011101001111010011110100011100100000001000000010000000100000000000000000000110000110101101000000000000000000000000000000000000000000000000000000000000000000000000000000000000000000000000000000000000000000000000000000000000000000000000000000000000000000000000000000000000000000000000000000000000000000000000000000000000000000000000000000000000000000000000000000000000000000000000000000000000000000 1
b1000001000100100011010001010110011110000000000000000000000000000000001001000010000000000000000000000011111010100100011101001111010011110100011100100000001000000010000000100000000000000000000110000110101101000000000000000000000000000000000000000000000000000000000000000000000000000000000000000000000000000000000000000000000000000000000000000000000000000000000000000000000000000000000000000000000000000000000000000000000000000000000000000000000000000000000000000000000000000000000000000000000000000000000000000000 3
b1000001000100100011010001010110011110000000000000000000000000000000001001000010000000000000000000000011111010100100011101001111010011110100011100100000001000000010000000100000000000000000000110000110101101000000000000000000000000000000000000000000000000000000000000000000000000000000000000000000000000000000000000000000000000000000000000000000000000000000000000000000000000000000000000000000000000000000000000000000000000000000000000000000000000000000000000000000000000000000000000000000000000000000000000000000 =
10
1!
#185000
0!
#190000
b0 1
b0 3
b0 =
00
12
b11000011010110100 (
b11000011010110100 5
b1111101010 '
b1111101010 6
b1001000110100010101100111100000000000000000000000000000000010 )
b1001000110100010101100111100000000000000000000000000000000010 4
1!
#195000
0!
#200000
b1000001000100100011010001010110011110000000000000000000000000000000000001000010000000000000000000000011111010000100011101001111010011110100011100100000001000000010000000100000000000000000000110000110101000000000000000000000000000000000000000000000000000000000000000000000000000000000000000000000000000000000000000000000000000000000000000000000000000000000000000000000000000000000000000000000000000000000000000000000000000000000000000000000000000000000000000000000000000000000000000000000000000000000000000000000 $
b1000001000100100011010001010110011110000000000000000000000000000000000001000010000000000000000000000011111010000100011101001111010011110100011100100000001000000010000000100000000000000000000110000110101000000000000000000000000000000000000000000000000000000000000000000000000000000000000000000000000000000000000000000000000000000000000000000000000000000000000000000000000000000000000000000000000000000000000000000000000000000000000000000000000000000000000000000000000000000000000000000000000000000000000000000000 <
1"
02
1!
#205000
0!
#210000
b0 &
b0 7
b0 (
b0 5
b0 '
b0 6
b0 )
b0 4
0%
b0 1
b0 3
b0 =
00
1!
#215000
0!
#220000
1%
1!
#225000
0!
#230000
0"
b1000001000100100011010001010110011110000000000000000000000000000000000001000010000000000000000000000011111010000100011101001111010011110100011100100000001000000010000000100000000000000000000110000110101000000000000000000000000000000000000000000000000000000000000000000000000000000000000000000000000000000000000000000000000000000000000000000000000000000000000000000000000000000000000000000000000000000000000000000000000000000000000000000000000000000000000000000000000000000000000000000000000000000000000000000000 1
b1000001000100100011010001010110011110000000000000000000000000000000000001000010000000000000000000000011111010000100011101001111010011110100011100100000001000000010000000100000000000000000000110000110101000000000000000000000000000000000000000000000000000000000000000000000000000000000000000000000000000000000000000000000000000000000000000000000000000000000000000000000000000000000000000000000000000000000000000000000000000000000000000000000000000000000000000000000000000000000000000000000000000000000000000000000 3
b1000001000100100011010001010110011110000000000000000000000000000000000001000010000000000000000000000011111010000100011101001111010011110100011100100000001000000010000000100000000000000000000110000110101000000000000000000000000000000000000000000000000000000000000000000000000000000000000000000000000000000000000000000000000000000000000000000000000000000000000000000000000000000000000000000000000000000000000000000000000000000000000000000000000000000000000000000000000000000000000000000000000000000000000000000000 =
10
1!
#235000
0!
#240000
b1011000110111101010110110111110111011111100101011111110101110101011111000000000000000000000001111101000000000000000000000000000000000000000000000000000000000000000000000000000000000000000000000000000000000000000000000000000000000000000000000000000000000000000000000000000000000000000000000000000000000000000000000000000000000000000000000000000000000000000000000000000000000000000000000000000000000000000000000000000000000000000000000000000000000000000000000000000000000000000000000000000000000000000000000000000 $
b1011000110111101010110110111110111011111100101011111110101110101011111000000000000000000000001111101000000000000000000000000000000000000000000000000000000000000000000000000000000000000000000000000000000000000000000000000000000000000000000000000000000000000000000000000000000000000000000000000000000000000000000000000000000000000000000000000000000000000000000000000000000000000000000000000000000000000000000000000000000000000000000000000000000000000000000000000000000000000000000000000000000000000000000000000000 <
b1011000 #
b1011000 ;
1"
b0 1
b0 3
b0 =
00
12
b11000011010100000 (
b11000011010100000 5
b100011101001111010011110100011100100000001000000010000000100000 &
b100011101001111010011110100011100100000001000000010000000100000 7
b1111101000 '
b1111101000 6
b1001000110100010101100111100000000000000000000000000000000000 )
b1001000110100010101100111100000000000000000000000000000000000 4
1!
#245000
0!
#250000
0"
02
b1011000110111101010110110111110111011111100101011111110101110101011111000000000000000000000001111101000000000000000000000000000000000000000000000000000000000000000000000000000000000000000000000000000000000000000000000000000000000000000000000000000000000000000000000000000000000000000000000000000000000000000000000000000000000000000000000000000000000000000000000000000000000000000000000000000000000000000000000000000000000000000000000000000000000000000000000000000000000000000000000000000000000000000000000000000 -
b1011000110111101010110110111110111011111100101011111110101110101011111000000000000000000000001111101000000000000000000000000000000000000000000000000000000000000000000000000000000000000000000000000000000000000000000000000000000000000000000000000000000000000000000000000000000000000000000000000000000000000000000000000000000000000000000000000000000000000000000000000000000000000000000000000000000000000000000000000000000000000000000000000000000000000000000000000000000000000000000000000000000000000000000000000000 8
b1011000110111101010110110111110111011111100101011111110101110101011111000000000000000000000001111101000000000000000000000000000000000000000000000000000000000000000000000000000000000000000000000000000000000000000000000000000000000000000000000000000000000000000000000000000000000000000000000000000000000000000000000000000000000000000000000000000000000000000000000000000000000000000000000000000000000000000000000000000000000000000000000000000000000000000000000000000000000000000000000000000000000000000000000000000 >
1+
1!
#255000
0!
#260000
b0 -
b0 8
b0 >
0+
1.
b1111101000 *
b1111101000 9
b1101111010101101101111101110111111001010111111101011101010111110 ,
b1101111010101101101111101110111111001010111111101011101010111110 :
1!
#265000
0!
#270000
0.
1!
#275000
0!
#280000
1!
#285000
0!
#290000
1!
#295000
0!
#300000
b111010011000011110000000000111111110110011010010100000110110010000010001110000010000000101100111100011111010100000111001101110001110111100011000110111011010001110011011111100010010010011101101001010000100111010101011010110010100100011010111101100010110001011101111111011100111010111111001000100110001000011110011000111110001101001010100110100001010111001111010101010100101010110001110101110101011101000100111101001001010001010100100011011010000011100011101100100011111001011111110101111000110001001101100011100 $
b111010011000011110000000000111111110110011010010100000110110010000010001110000010000000101100111100011111010100000111001101110001110111100011000110111011010001110011011111100010010010011101101001010000100111010101011010110010100100011010111101100010110001011101111111011100111010111111001000100110001000011110011000111110001101001010100110100001010111001111010101010100101010110001110101110101011101000100111101001001010001010100100011011010000011100011101100100011111001011111110101111000110001001101100011100 <
b1100010 #
b1100010 ;
1"
1!
#305000
0!
#310000
0"
1!
#315000
0!
#320000
b1000001000000000000000000000000000000000000000000000000000000000000000000000000000000000000000000000000000000000000000000000000000000000000000000000000000000000000000000000000000000000000000000000000000000000000000000000000000000000000000000000000000000000000000000000000000000000000000000000000000000000000000000000000000000000000000000000000000000000000000000000000000000000000000000000000000000000000000000000000000000000000000000000000000000000000000000000000000000000000000000000000000000000000000000000000 $
b1000001000000000000000000000000000000000000000000000000000000000000000000000000000000000000000000000000000000000000000000000000000000000000000000000000000000000000000000000000000000000000000000000000000000000000000000000000000000000000000000000000000000000000000000000000000000000000000000000000000000000000000000000000000000000000000000000000000000000000000000000000000000000000000000000000000000000000000000000000000000000000000000000000000000000000000000000000000000000000000000000000000000000000000000000000 <
b1000001 #
b1000001 ;
1"
1!
#325000
0!
#330000
0"
b1000001000000000000000000000000000000000000000000000000000000000000000000000000000000000000000000000000000000000000000000000000000000000000000000000000000000000000000000000000000000000000000000000000000000000000000000000000000000000000000000000000000000000000000000000000000000000000000000000000000000000000000000000000000000000000000000000000000000000000000000000000000000000000000000000000000000000000000000000000000000000000000000000000000000000000000000000000000000000000000000000000000000000000000000000000 1
b1000001000000000000000000000000000000000000000000000000000000000000000000000000000000000000000000000000000000000000000000000000000000000000000000000000000000000000000000000000000000000000000000000000000000000000000000000000000000000000000000000000000000000000000000000000000000000000000000000000000000000000000000000000000000000000000000000000000000000000000000000000000000000000000000000000000000000000000000000000000000000000000000000000000000000000000000000000000000000000000000000000000000000000000000000000 3
b1000001000000000000000000000000000000000000000000000000000000000000000000000000000000000000000000000000000000000000000000000000000000000000000000000000000000000000000000000000000000000000000000000000000000000000000000000000000000000000000000000000000000000000000000000000000000000000000000000000000000000000000000000000000000000000000000000000000000000000000000000000000000000000000000000000000000000000000000000000000000000000000000000000000000000000000000000000000000000000000000000000000000000000000000000000 =
10
1!
#335000
0!
#340000
b1011010000000000000000000000000000000000000000000000000000000000000000000000000000000000000000000000000000000000000000000000000000000000000000000000000000000000000000000000000000000000000000000000000000000000000000000000000000000000000000000000000000000000000000000000000000000000000000000000000000000000000000000000000000000000000000000000000000000000000000000000000000000000000000000000000000000000000000000000000000000000000000000000000000000000000000000000000000000000000000000000000000000000000000000000000 $
b1011010000000000000000000000000000000000000000000000000000000000000000000000000000000000000000000000000000000000000000000000000000000000000000000000000000000000000000000000000000000000000000000000000000000000000000000000000000000000000000000000000000000000000000000000000000000000000000000000000000000000000000000000000000000000000000000000000000000000000000000000000000000000000000000000000000000000000000000000000000000000000000000000000000000000000000000000000000000000000000000000000000000000000000000000000 <
b1011010 #
b1011010 ;
1"
b0 1
b0 3
b0 =
00
12
b0 (
b0 5
b0 &
b0 7
b0 '
b0 6
b0 )
b0 4
1!
#345000
0!
#350000
0"
02
1!
#355000
0!
#360000
b1011000110111101010110110111110111011111100101011111110101110101011111000000000000000000000001111101000000000000000000000000000000000000000000000000000000000000000000000000000000000000000000000000000000000000000000000000000000000000000000000000000000000000000000000000000000000000000000000000000000000000000000000000000000000000000000000000000000000000000000000000000000000000000000000000000000000000000000000000000000000000000000000000000000000000000000000000000000000000000000000000000000000000000000000000000 $
b1011000110111101010110110111110111011111100101011111110101110101011111000000000000000000000001111101000000000000000000000000000000000000000000000000000000000000000000000000000000000000000000000000000000000000000000000000000000000000000000000000000000000000000000000000000000000000000000000000000000000000000000000000000000000000000000000000000000000000000000000000000000000000000000000000000000000000000000000000000000000000000000000000000000000000000000000000000000000000000000000000000000000000000000000000000 <
b1011000 #
b1011000 ;
1"
1!
#365000
0!
#370000
0"
b1011000110111101010110110111110111011111100101011111110101110101011111000000000000000000000001111101000000000000000000000000000000000000000000000000000000000000000000000000000000000000000000000000000000000000000000000000000000000000000000000000000000000000000000000000000000000000000000000000000000000000000000000000000000000000000000000000000000000000000000000000000000000000000000000000000000000000000000000000000000000000000000000000000000000000000000000000000000000000000000000000000000000000000000000000000 -
b1011000110111101010110110111110111011111100101011111110101110101011111000000000000000000000001111101000000000000000000000000000000000000000000000000000000000000000000000000000000000000000000000000000000000000000000000000000000000000000000000000000000000000000000000000000000000000000000000000000000000000000000000000000000000000000000000000000000000000000000000000000000000000000000000000000000000000000000000000000000000000000000000000000000000000000000000000000000000000000000000000000000000000000000000000000 8
b1011000110111101010110110111110111011111100101011111110101110101011111000000000000000000000001111101000000000000000000000000000000000000000000000000000000000000000000000000000000000000000000000000000000000000000000000000000000000000000000000000000000000000000000000000000000000000000000000000000000000000000000000000000000000000000000000000000000000000000000000000000000000000000000000000000000000000000000000000000000000000000000000000000000000000000000000000000000000000000000000000000000000000000000000000000 >
1+
1!
#375000
0!
#380000
b0 -
b0 8
b0 >
0+
1.
1!
#385000
0!
#390000
b1011000110111101010110110111110111011111100101011111110101110101011111100000000000000000000001111101101000000000000000000000000000000000000000000000000000000000000000000000000000000000000000000000000000000000000000000000000000000000000000000000000000000000000000000000000000000000000000000000000000000000000000000000000000000000000000000000000000000000000000000000000000000000000000000000000000000000000000000000000000000000000000000000000000000000000000000000000000000000000000000000000000000000000000000000000 $
b1011000110111101010110110111110111011111100101011111110101110101011111100000000000000000000001111101101000000000000000000000000000000000000000000000000000000000000000000000000000000000000000000000000000000000000000000000000000000000000000000000000000000000000000000000000000000000000000000000000000000000000000000000000000000000000000000000000000000000000000000000000000000000000000000000000000000000000000000000000000000000000000000000000000000000000000000000000000000000000000000000000000000000000000000000000 <
1"
0.
1!
#395000
0!
#400000
0"
b1011000110111101010110110111110111011111100101011111110101110101011111100000000000000000000001111101101000000000000000000000000000000000000000000000000000000000000000000000000000000000000000000000000000000000000000000000000000000000000000000000000000000000000000000000000000000000000000000000000000000000000000000000000000000000000000000000000000000000000000000000000000000000000000000000000000000000000000000000000000000000000000000000000000000000000000000000000000000000000000000000000000000000000000000000000 -
b1011000110111101010110110111110111011111100101011111110101110101011111100000000000000000000001111101101000000000000000000000000000000000000000000000000000000000000000000000000000000000000000000000000000000000000000000000000000000000000000000000000000000000000000000000000000000000000000000000000000000000000000000000000000000000000000000000000000000000000000000000000000000000000000000000000000000000000000000000000000000000000000000000000000000000000000000000000000000000000000000000000000000000000000000000000 8
b1011000110111101010110110111110111011111100101011111110101110101011111100000000000000000000001111101101000000000000000000000000000000000000000000000000000000000000000000000000000000000000000000000000000000000000000000000000000000000000000000000000000000000000000000000000000000000000000000000000000000000000000000000000000000000000000000000000000000000000000000000000000000000000000000000000000000000000000000000000000000000000000000000000000000000000000000000000000000000000000000000000000000000000000000000000 >
1+
1!
#405000
0!
#410000
1.
b1111101101 *
b1111101101 9
b1101111010101101101111101110111111001010111111101011101010111111 ,
b1101111010101101101111101110111111001010111111101011101010111111 :
b0 -
b0 8
b0 >
0+
1!
#415000
0!
