Design/rtl/cancel_order_decoder.v
// =============================================
// cancel_order_decoder.v
// =============================================
//
// Description: Module to decode Cancel Order ('X') messages from ITCH payloads.
// Author: RZ
// Start Date: 04172025
// Version: 0.4
// Changelog
// =============================================
// [20250427-1] RZ: Initial version created for Cancel Order payload decoding.
// [20250428-1] RZ: Updated ports and internal signals for dispatcher integration.
// [20250428-2] RZ: Added valid_flag signal 
// [20250501-1] RZ: Initial implementation based on add_order_decoder structure with new arch.
// 
// =============================================
// ------------------------------------------------------------------------------------------------
// Architecture Notes:
// ------------------------------------------------------------------------------------------------
// The ITCH "Cancel Order" ('X') message has a fixed length of 23 bytes and is structured as:
//   [0]      = Message Type (ASCII 'X')
//   [1:8]    = Order Reference Number (64-bit)
//   [9:12]   = Canceled Shares (32-bit)
//   [13:22]  = Reserved bytes (ignored)
//
// This decoder consumes a byte-aligned, per-cycle stream of ITCH bytes and speculatively 
// begins parsing at cycle 0. On cycle 0, it captures the message type and immediately decodes
// byte 1 as `order_ref[63:56]`. Parallel validation confirms whether the message is of type 'X'.
// The decoder asserts `internal_valid` after 23 valid cycles only if the type matches.
//
// Inputs:
//   - clk            : system clock
//   - rst            : synchronous reset
//   - byte_in[7:0]   : ITCH byte stream (1 byte per cycle)
//   - valid_in       : asserted high when byte_in is valid
//
// Outputs:
//   - internal_valid : one-cycle pulse when a valid Cancel Order message is fully parsed
//   - packet_invalid : asserted if message length overruns unexpectedly (optional use)
//   - order_ref      : 64-bit parsed order reference number
//   - canceled_shares: 32-bit parsed canceled share quantity
// ------------------------------------------------------------------------------------------------
module cancel_order_decoder (
    input  logic        clk,
    input  logic        rst,
    input  logic [7:0]  byte_in,
    input  logic        valid_in,

    output logic        cancel_internal_valid,
    output logic        cancel_packet_invalid,

    output logic [63:0] cancel_order_ref,
    output logic [31:0] cancel_canceled_shares
);

    parameter MSG_TYPE   = 8'h58;   // ASCII 'X'
    parameter MSG_LENGTH = 23;

    // ITCH message length mapping
    function automatic logic [5:0] itch_length(input logic [7:0] msg_type);
        case (msg_type)
            "A": return 36;
            "X": return 23;
            "U": return 27;
            "D": return 9;
            "E": return 30;
            "P": return 44;
            default: return 2;
        endcase
    endfunction

    logic [5:0] suppress_count;
    logic [5:0] byte_index;
    logic       is_cancel_order;

    wire decoder_enabled = (suppress_count == 0);

    // Suppression counter
    always_ff @(posedge clk) begin
        if (rst) begin
            suppress_count <= 0;
        end else if (suppress_count != 0) begin
            suppress_count <= suppress_count - 1;
        end
    end

    always_ff @(posedge clk) begin
        if (rst) begin
            byte_index              <= 0;
            is_cancel_order         <= 0;
            cancel_internal_valid   <= 0;
            cancel_packet_invalid   <= 0;
            cancel_order_ref        <= 0;
            cancel_canceled_shares  <= 0;
        end else if (valid_in && decoder_enabled) begin
            cancel_internal_valid <= 0;
            cancel_packet_invalid <= 0;

            if (byte_index == 0) begin
                is_cancel_order <= (byte_in == MSG_TYPE);
                if (byte_in == MSG_TYPE)
                    byte_index <= 1;
                else begin
                    suppress_count     <= itch_length(byte_in) - 2;
                    is_cancel_order    <= 0;
                    byte_index         <= 0;
                end
            end else begin
                byte_index <= byte_index + 1;
            end

            if (is_cancel_order) begin
                case (byte_index)
                    1:  cancel_order_ref[63:56]       <= byte_in;
                    2:  cancel_order_ref[55:48]       <= byte_in;
                    3:  cancel_order_ref[47:40]       <= byte_in;
                    4:  cancel_order_ref[39:32]       <= byte_in;
                    5:  cancel_order_ref[31:24]       <= byte_in;
                    6:  cancel_order_ref[23:16]       <= byte_in;
                    7:  cancel_order_ref[15:8]        <= byte_in;
                    8:  cancel_order_ref[7:0]         <= byte_in;
                    9:  cancel_canceled_shares[31:24] <= byte_in;
                    10: cancel_canceled_shares[23:16] <= byte_in;
                    11: cancel_canceled_shares[15:8]  <= byte_in;
                    12: cancel_canceled_shares[7:0]   <= byte_in;
                endcase

                if (byte_index == MSG_LENGTH - 1)
                    cancel_internal_valid <= 1;
            end

            if (byte_index >= MSG_LENGTH && is_cancel_order)
                cancel_packet_invalid <= 1;
        end

        // Defensive invalid packet catch
        if (is_cancel_order && (
            (valid_in == 0 && byte_index > 0 && byte_index < MSG_LENGTH) ||
            (byte_index >= MSG_LENGTH)
        ))
            cancel_packet_invalid <= 1;

        // --- Clear or prepare for next ---
        if (byte_index == MSG_LENGTH) begin
            cancel_internal_valid   <= 0;
            cancel_packet_invalid   <= 0;
            cancel_order_ref        <= 0;
            cancel_canceled_shares  <= 0;

            if (valid_in && byte_in == MSG_TYPE) begin
                is_cancel_order <= 1;
                byte_index      <= 1;
            end else if (valid_in) begin
                is_cancel_order <= 0;
                byte_index      <= 0;
                suppress_count  <= itch_length(byte_in) - 2;
            end else begin
                is_cancel_order <= 0;
                byte_index      <= 0;
            end
        end
    end

endmodule

Design/rtl/add_order_decoder.v
// =============================================
// add_order_decoder.v
// =============================================
//
// Description: Zero-wait speculative Add Order decoder for ITCH feed.
//              Begins decoding at byte 0 and maps order_ref from byte 1.
// Author: RZ
// Start Date: 20250430
// Version: 0.6
//
// Changelog
// =============================================
// [20250430-1] RZ: Initial speculative streaming implementation.
// [20250501-1] RZ: Renamed misc_data to stock_symbol.
// [20250501-2] RZ: Fixed byte index off-by-one.
// [20250501-3] RZ: Fully speculative decode without waiting for type match.
// [20250501-4] RZ: Rebased order_ref to start at byte 1 (byte 0 is msg_type).
// [20250502-1] RZ: Added self disable and zeroing of signals after message parsing completion.
// =============================================

// ------------------------------------------------------------------------------------------------
// Architecture Notes:
// ------------------------------------------------------------------------------------------------
// The ITCH "Add Order" ('A') message has a fixed length of 36 bytes and is structured as:
//   [0]     = Message Type (ASCII 'A')
//   [1:8]   = Order Reference Number (64-bit)
//   [9]     = Buy/Sell Indicator ('B' or 'S')
//   [10:13] = Number of Shares (32-bit)
//   [14:21] = Stock Symbol (8 ASCII characters, space-padded)
//   [22:25] = Price (32-bit, fixed-point with 4 implied decimal places)
//
// This decoder consumes a byte-alWigned, per-cycle stream of ITCH bytes and speculatively 
// begins parsing at cycle 0. On cycle 0, it captures the message type and immediately decodes
// byte 1 as `order_ref[63:56]`. Parallel validation confirms whether the message is of type 'A'.
// The decoder asserts `internal_valid` after 36 valid cycles only if the type matches.
//
// Inputs:
//   - clk           : system clock
//   - rst           : synchronous reset
//   - byte_in[7:0]  : ITCH byte stream (1 byte per cycle)
//   - valid_in      : asserted high when byte_in is valid
//
// Outputs:
//   - internal_valid: one-cycle pulse when a valid Add Order message is fully parsed
//   - packet_invalid: asserted if message length overruns unexpectedly (optional use)
//   - order_ref     : 64-bit parsed order reference number
//   - side          : 1-bit flag, 1 = sell ('S'), 0 = buy ('B')
//   - shares        : 32-bit parsed number of shares
//   - price         : 32-bit fixed-point price
//   - stock_symbol  : 64-bit ASCII stock symbol (left-justified, space-padded)
// ------------------------------------------------------------------------------------------------
module add_order_decoder (
    input  logic        clk,
    input  logic        rst,
    input  logic [7:0]  byte_in,
    input  logic        valid_in,

    output logic        add_internal_valid,
    output logic        add_packet_invalid,

    output logic [63:0] add_order_ref,
    output logic        add_side,
    output logic [31:0] add_shares,
    output logic [31:0] add_price,
    output logic [63:0] add_stock_symbol
);

    parameter MSG_TYPE   = 8'h41;   // ASCII 'A'
    parameter MSG_LENGTH = 36;

    function automatic logic [5:0] itch_length(input logic [7:0] msg_type);
        case (msg_type)
            "A": return 36;
            "X": return 23;
            "U": return 27;
            "D": return 9;
            "E": return 30;
            "P": return 44;
            default: return 2;
        endcase
    endfunction

    logic [5:0] suppress_count;
    logic [5:0] byte_index;
    logic       is_add_order;

    wire decoder_enabled = (suppress_count == 0);

    // Suppression logic
    always_ff @(posedge clk) begin
        if (rst) begin
            suppress_count <= 0;
        end else if (suppress_count != 0) begin
            suppress_count <= suppress_count - 1;
        end
    end

    // Main decode logic
    always_ff @(posedge clk) begin
        if (rst) begin
            byte_index         <= 0;
            is_add_order       <= 0;
            add_internal_valid <= 0;
            add_packet_invalid <= 0;
            add_order_ref      <= 0;
            add_side           <= 0;
            add_shares         <= 0;
            add_price          <= 0;
            add_stock_symbol   <= 0;
        end else if (valid_in && decoder_enabled) begin
            add_internal_valid <= 0;
            add_packet_invalid <= 0;

            if (byte_index == 0) begin
                is_add_order <= (byte_in == MSG_TYPE);
                if (byte_in == MSG_TYPE)
                    byte_index <= 1;
                else begin
                    suppress_count <= itch_length(byte_in) - 2;
                    is_add_order   <= 0;
                    byte_index     <= 0;
                end
            end else begin
                byte_index <= byte_index + 1;
            end

            if (is_add_order) begin
                case (byte_index)
                    1:  add_order_ref[63:56]     <= byte_in;
                    2:  add_order_ref[55:48]     <= byte_in;
                    3:  add_order_ref[47:40]     <= byte_in;
                    4:  add_order_ref[39:32]     <= byte_in;
                    5:  add_order_ref[31:24]     <= byte_in;
                    6:  add_order_ref[23:16]     <= byte_in;
                    7:  add_order_ref[15:8]      <= byte_in;
                    8:  add_order_ref[7:0]       <= byte_in;
                    9:  add_side                 <= (byte_in == "S");
                    10: add_shares[31:24]        <= byte_in;
                    11: add_shares[23:16]        <= byte_in;
                    12: add_shares[15:8]         <= byte_in;
                    13: add_shares[7:0]          <= byte_in;
                    14: add_stock_symbol[63:56]  <= byte_in;
                    15: add_stock_symbol[55:48]  <= byte_in;
                    16: add_stock_symbol[47:40]  <= byte_in;
                    17: add_stock_symbol[39:32]  <= byte_in;
                    18: add_stock_symbol[31:24]  <= byte_in;
                    19: add_stock_symbol[23:16]  <= byte_in;
                    20: add_stock_symbol[15:8]   <= byte_in;
                    21: add_stock_symbol[7:0]    <= byte_in;
                    22: add_price[31:24]         <= byte_in;
                    23: add_price[23:16]         <= byte_in;
                    24: add_price[15:8]          <= byte_in;
                    25: add_price[7:0]           <= byte_in;
                endcase

                if (byte_index == MSG_LENGTH - 1)
                    add_internal_valid <= 1;
            end

            if (byte_index >= MSG_LENGTH && is_add_order)
                add_packet_invalid <= 1;
        end

        if (is_add_order && (
            (valid_in == 0 && byte_index > 0 && byte_index < MSG_LENGTH) ||
            (byte_index >= MSG_LENGTH)
        ))
            add_packet_invalid <= 1;

        // --- Reset or prepare next ---
        if (byte_index == MSG_LENGTH) begin
            add_internal_valid <= 0;
            add_packet_invalid <= 0;
            add_order_ref      <= 0;
            add_side           <= 0;
            add_shares         <= 0;
            add_price          <= 0;
            add_stock_symbol   <= 0;

            if (valid_in && byte_in == MSG_TYPE) begin
                is_add_order <= 1;
                byte_index   <= 1;
            end else if (valid_in) begin
                is_add_order   <= 0;
                byte_index     <= 0;
                suppress_count <= itch_length(byte_in) - 2;
            end else begin
                is_add_order <= 0;
                byte_index   <= 0;
            end
        end
    end

endmodule

Design/rtl/integrated.v

// =====================================================
// integrated.v
// =====================================================
// Description: Integrated ITCH parser with Add and Cancel decoders
// =====================================================

module integrated (
    input  logic        clk,
    input  logic        rst,
    input  logic [7:0]  byte_in,
    input  logic        valid_in,

    output logic        add_internal_valid,
    output logic        cancel_internal_valid
);

    // Ignoring unused outputs for now
    logic        add_packet_invalid;
    logic [63:0] add_order_ref;
    logic        add_side;
    logic [31:0] add_shares;
    logic [31:0] add_price;
    logic [63:0] add_stock_symbol;

    logic        cancel_packet_invalid;
    logic [63:0] cancel_order_ref;
    logic [31:0] cancel_canceled_shares;

    add_order_decoder u_add (
        .clk(clk),
        .rst(rst),
        .byte_in(byte_in),
        .valid_in(valid_in),
        .add_internal_valid(add_internal_valid),
        .add_packet_invalid(add_packet_invalid),
        .add_order_ref(add_order_ref),
        .add_side(add_side),
        .add_shares(add_shares),
        .add_price(add_price),
        .add_stock_symbol(add_stock_symbol)
    );

    cancel_order_decoder u_cancel (
        .clk(clk),
        .rst(rst),
        .byte_in(byte_in),
        .valid_in(valid_in),
        .cancel_internal_valid(cancel_internal_valid),
        .cancel_packet_invalid(cancel_packet_invalid),
        .cancel_order_ref(cancel_order_ref),
        .cancel_canceled_shares(cancel_canceled_shares)
    );


            // ======================= Waveform Dump =======================
            `ifdef COCOTB_SIM
            initial begin
                $dumpfile("dump.vcd");
                $dumpvars(0, integrated);
            end
            `endif

endmodule

Design/sim/vcd/integrated_dump_05022025_213748.vcd
$date
	Fri May  2 21:37:55 2025
$end
$version
	Icarus Verilog
$end
$timescale
	1ps
$end
$scope module integrated $end
$var wire 8 ! byte_in [7:0] $end
$var wire 1 " clk $end
$var wire 1 # rst $end
$var wire 1 $ valid_in $end
$var wire 1 % cancel_packet_invalid $end
$var wire 64 & cancel_order_ref [63:0] $end
$var wire 1 ' cancel_internal_valid $end
$var wire 32 ( cancel_canceled_shares [31:0] $end
$var wire 64 ) add_stock_symbol [63:0] $end
$var wire 1 * add_side $end
$var wire 32 + add_shares [31:0] $end
$var wire 32 , add_price [31:0] $end
$var wire 1 - add_packet_invalid $end
$var wire 64 . add_order_ref [63:0] $end
$var wire 1 / add_internal_valid $end
$scope module u_add $end
$var wire 8 0 byte_in [7:0] $end
$var wire 1 " clk $end
$var wire 1 # rst $end
$var wire 1 $ valid_in $end
$var wire 1 1 decoder_enabled $end
$var reg 1 / add_internal_valid $end
$var reg 64 2 add_order_ref [63:0] $end
$var reg 1 - add_packet_invalid $end
$var reg 32 3 add_price [31:0] $end
$var reg 32 4 add_shares [31:0] $end
$var reg 1 * add_side $end
$var reg 64 5 add_stock_symbol [63:0] $end
$var reg 6 6 byte_index [5:0] $end
$var reg 1 7 is_add_order $end
$var reg 6 8 suppress_count [5:0] $end
$scope function itch_length $end
$upscope $end
$upscope $end
$scope module u_cancel $end
$var wire 8 9 byte_in [7:0] $end
$var wire 1 " clk $end
$var wire 1 # rst $end
$var wire 1 $ valid_in $end
$var wire 1 : decoder_enabled $end
$var reg 6 ; byte_index [5:0] $end
$var reg 32 < cancel_canceled_shares [31:0] $end
$var reg 1 ' cancel_internal_valid $end
$var reg 64 = cancel_order_ref [63:0] $end
$var reg 1 % cancel_packet_invalid $end
$var reg 1 > is_cancel_order $end
$var reg 6 ? suppress_count [5:0] $end
$scope function itch_length $end
$upscope $end
$upscope $end
$upscope $end
$enddefinitions $end
#0
$dumpvars
b0 ?
0>
b0 =
b0 <
b0 ;
1:
b0 9
b0 8
07
b0 6
b0 5
b0 4
b0 3
b0 2
11
b0 0
0/
b0 .
0-
b0 ,
b0 +
0*
b0 )
b0 (
0'
b0 &
0%
0$
1#
1"
b0 !
$end
#5000
0"
#10000
1"
#15000
0"
#20000
1$
b1000001 !
b1000001 0
b1000001 9
0#
1"
#25000
0"
#30000
b1 !
b1 0
b1 9
b1 ;
b1 6
17
1"
#35000
0"
#40000
b100011 !
b100011 0
b100011 9
b10 6
b100000000000000000000000000000000000000000000000000000000 .
b100000000000000000000000000000000000000000000000000000000 2
b10 ;
1"
#45000
0"
#50000
b1000101 !
b1000101 0
b1000101 9
b11 ;
b11 6
b100100011000000000000000000000000000000000000000000000000 .
b100100011000000000000000000000000000000000000000000000000 2
1"
#55000
0"
#60000
b1100111 !
b1100111 0
b1100111 9
b100 6
b100100011010001010000000000000000000000000000000000000000 .
b100100011010001010000000000000000000000000000000000000000 2
b100 ;
1"
#65000
0"
#70000
b10001001 !
b10001001 0
b10001001 9
b101 ;
b101 6
b100100011010001010110011100000000000000000000000000000000 .
b100100011010001010110011100000000000000000000000000000000 2
1"
#75000
0"
#80000
b10101011 !
b10101011 0
b10101011 9
b110 6
b100100011010001010110011110001001000000000000000000000000 .
b100100011010001010110011110001001000000000000000000000000 2
b110 ;
1"
#85000
0"
#90000
b11001101 !
b11001101 0
b11001101 9
b111 ;
b111 6
b100100011010001010110011110001001101010110000000000000000 .
b100100011010001010110011110001001101010110000000000000000 2
1"
#95000
0"
#100000
b11101111 !
b11101111 0
b11101111 9
b1000 6
b100100011010001010110011110001001101010111100110100000000 .
b100100011010001010110011110001001101010111100110100000000 2
b1000 ;
1"
#105000
0"
#110000
b1000010 !
b1000010 0
b1000010 9
b1001 ;
b1001 6
b100100011010001010110011110001001101010111100110111101111 .
b100100011010001010110011110001001101010111100110111101111 2
1"
#115000
0"
#120000
b0 !
b0 0
b0 9
b1010 6
b1010 ;
1"
#125000
0"
#130000
b1011 ;
b1011 6
1"
#135000
0"
#140000
b1100 6
b1100 ;
1"
#145000
0"
#150000
b1100100 !
b1100100 0
b1100100 9
b1101 ;
b1101 6
1"
#155000
0"
#160000
b1000001 !
b1000001 0
b1000001 9
b1110 6
b1100100 +
b1100100 4
b1110 ;
1"
#165000
0"
#170000
b1000010 !
b1000010 0
b1000010 9
b1111 ;
b1111 6
b100000100000000000000000000000000000000000000000000000000000000 )
b100000100000000000000000000000000000000000000000000000000000000 5
1"
#175000
0"
#180000
b1000011 !
b1000011 0
b1000011 9
b10000 6
b100000101000010000000000000000000000000000000000000000000000000 )
b100000101000010000000000000000000000000000000000000000000000000 5
b10000 ;
1"
#185000
0"
#190000
b1000100 !
b1000100 0
b1000100 9
b10001 ;
b10001 6
b100000101000010010000110000000000000000000000000000000000000000 )
b100000101000010010000110000000000000000000000000000000000000000 5
1"
#195000
0"
#200000
b110001 !
b110001 0
b110001 9
b10010 6
b100000101000010010000110100010000000000000000000000000000000000 )
b100000101000010010000110100010000000000000000000000000000000000 5
b10010 ;
1"
#205000
0"
#210000
b110010 !
b110010 0
b110010 9
b10011 ;
b10011 6
b100000101000010010000110100010000110001000000000000000000000000 )
b100000101000010010000110100010000110001000000000000000000000000 5
1"
#215000
0"
#220000
b110011 !
b110011 0
b110011 9
b10100 6
b100000101000010010000110100010000110001001100100000000000000000 )
b100000101000010010000110100010000110001001100100000000000000000 5
b10100 ;
1"
#225000
0"
#230000
b110100 !
b110100 0
b110100 9
b10101 ;
b10101 6
b100000101000010010000110100010000110001001100100011001100000000 )
b100000101000010010000110100010000110001001100100011001100000000 5
1"
#235000
0"
#240000
b0 !
b0 0
b0 9
b10110 6
b100000101000010010000110100010000110001001100100011001100110100 )
b100000101000010010000110100010000110001001100100011001100110100 5
b10110 ;
1"
#245000
0"
#250000
b10111 ;
b10111 6
1"
#255000
0"
#260000
b1111 !
b1111 0
b1111 9
b11000 6
b0 ;
1"
#265000
0"
#270000
b10100000 !
b10100000 0
b10100000 9
b1 ;
b11001 6
b111100000000 ,
b111100000000 3
1"
#275000
0"
#280000
b1 !
b1 0
b1 9
b11010 6
b111110100000 ,
b111110100000 3
b10 ;
1"
#285000
0"
#290000
b10 !
b10 0
b10 9
b11 ;
b11011 6
1"
#295000
0"
#300000
b11 !
b11 0
b11 9
b11100 6
b100 ;
1"
#305000
0"
#310000
b100 !
b100 0
b100 9
b101 ;
b11101 6
1"
#315000
0"
#320000
b101 !
b101 0
b101 9
b11110 6
b110 ;
1"
#325000
0"
#330000
b110 !
b110 0
b110 9
b111 ;
b11111 6
1"
#335000
0"
#340000
b111 !
b111 0
b111 9
b100000 6
b1000 ;
1"
#345000
0"
#350000
b1000 !
b1000 0
b1000 9
b1001 ;
b100001 6
1"
#355000
0"
#360000
b1001 !
b1001 0
b1001 9
b100010 6
b1010 ;
1"
#365000
0"
#370000
b1010 !
b1010 0
b1010 9
b1011 ;
b100011 6
1"
#375000
0"
#380000
b1000001 !
b1000001 0
b1000001 9
b100100 6
1/
b1100 ;
1"
#385000
0"
#390000
b1 !
b1 0
b1 9
b1101 ;
b0 )
b0 5
b0 ,
b0 3
b0 +
b0 4
b0 .
b0 2
0-
b1 6
0/
1"
#395000
0"
#400000
b100011 !
b100011 0
b100011 9
b10 6
b100000000000000000000000000000000000000000000000000000000 .
b100000000000000000000000000000000000000000000000000000000 2
b1110 ;
1"
#405000
0"
#410000
b1000101 !
b1000101 0
b1000101 9
b1111 ;
b11 6
b100100011000000000000000000000000000000000000000000000000 .
b100100011000000000000000000000000000000000000000000000000 2
1"
#415000
0"
#420000
b1100111 !
b1100111 0
b1100111 9
b100 6
b100100011010001010000000000000000000000000000000000000000 .
b100100011010001010000000000000000000000000000000000000000 2
b10000 ;
1"
#425000
0"
#430000
b10001001 !
b10001001 0
b10001001 9
b10001 ;
b101 6
b100100011010001010110011100000000000000000000000000000000 .
b100100011010001010110011100000000000000000000000000000000 2
1"
#435000
0"
#440000
b10101011 !
b10101011 0
b10101011 9
b110 6
b100100011010001010110011110001001000000000000000000000000 .
b100100011010001010110011110001001000000000000000000000000 2
b10010 ;
1"
#445000
0"
#450000
b11001101 !
b11001101 0
b11001101 9
b10011 ;
b111 6
b100100011010001010110011110001001101010110000000000000000 .
b100100011010001010110011110001001101010110000000000000000 2
1"
#455000
0"
#460000
b11101111 !
b11101111 0
b11101111 9
b1000 6
b100100011010001010110011110001001101010111100110100000000 .
b100100011010001010110011110001001101010111100110100000000 2
b10100 ;
1"
#465000
0"
#470000
b1000010 !
b1000010 0
b1000010 9
b10101 ;
b1001 6
b100100011010001010110011110001001101010111100110111101111 .
b100100011010001010110011110001001101010111100110111101111 2
1"
#475000
0"
#480000
b0 !
b0 0
b0 9
b1010 6
b10110 ;
1"
#485000
0"
#490000
b10111 ;
b1011 6
1"
#495000
0"
#500000
b1100 6
b0 ;
1"
#505000
0"
#510000
b1100100 !
b1100100 0
b1100100 9
b1 ;
b1101 6
1"
#515000
0"
#520000
b1000001 !
b1000001 0
b1000001 9
b1110 6
b1100100 +
b1100100 4
b10 ;
1"
#525000
0"
#530000
b1000010 !
b1000010 0
b1000010 9
b11 ;
b1111 6
b100000100000000000000000000000000000000000000000000000000000000 )
b100000100000000000000000000000000000000000000000000000000000000 5
1"
#535000
0"
#540000
b1000011 !
b1000011 0
b1000011 9
b10000 6
b100000101000010000000000000000000000000000000000000000000000000 )
b100000101000010000000000000000000000000000000000000000000000000 5
b100 ;
1"
#545000
0"
#550000
b1000100 !
b1000100 0
b1000100 9
b101 ;
b10001 6
b100000101000010010000110000000000000000000000000000000000000000 )
b100000101000010010000110000000000000000000000000000000000000000 5
1"
#555000
0"
#560000
b110001 !
b110001 0
b110001 9
b10010 6
b100000101000010010000110100010000000000000000000000000000000000 )
b100000101000010010000110100010000000000000000000000000000000000 5
b110 ;
1"
#565000
0"
#570000
b110010 !
b110010 0
b110010 9
b111 ;
b10011 6
b100000101000010010000110100010000110001000000000000000000000000 )
b100000101000010010000110100010000110001000000000000000000000000 5
1"
#575000
0"
#580000
b110011 !
b110011 0
b110011 9
b10100 6
b100000101000010010000110100010000110001001100100000000000000000 )
b100000101000010010000110100010000110001001100100000000000000000 5
b1000 ;
1"
#585000
0"
#590000
b110100 !
b110100 0
b110100 9
b1001 ;
b10101 6
b100000101000010010000110100010000110001001100100011001100000000 )
b100000101000010010000110100010000110001001100100011001100000000 5
1"
#595000
0"
#600000
b0 !
b0 0
b0 9
b10110 6
b100000101000010010000110100010000110001001100100011001100110100 )
b100000101000010010000110100010000110001001100100011001100110100 5
b1010 ;
1"
#605000
0"
#610000
b1011 ;
b10111 6
1"
#615000
0"
#620000
b1111 !
b1111 0
b1111 9
b11000 6
b1100 ;
1"
#625000
0"
#630000
b10100000 !
b10100000 0
b10100000 9
b1101 ;
b11001 6
b111100000000 ,
b111100000000 3
1"
#635000
0"
#640000
b1 !
b1 0
b1 9
b11010 6
b111110100000 ,
b111110100000 3
b1110 ;
1"
#645000
0"
#650000
b10 !
b10 0
b10 9
b1111 ;
b11011 6
1"
#655000
0"
#660000
b11 !
b11 0
b11 9
b11100 6
b10000 ;
1"
#665000
0"
#670000
b100 !
b100 0
b100 9
b10001 ;
b11101 6
1"
#675000
0"
#680000
b101 !
b101 0
b101 9
b11110 6
b10010 ;
1"
#685000
0"
#690000
b110 !
b110 0
b110 9
b10011 ;
b11111 6
1"
#695000
0"
#700000
b111 !
b111 0
b111 9
b100000 6
b10100 ;
1"
#705000
0"
#710000
b1000 !
b1000 0
b1000 9
b10101 ;
b100001 6
1"
#715000
0"
#720000
b1001 !
b1001 0
b1001 9
b100010 6
b10110 ;
1"
#725000
0"
#730000
b1010 !
b1010 0
b1010 9
b10111 ;
b100011 6
1"
#735000
0"
#740000
b1011000 !
b1011000 0
b1011000 9
b100100 6
1/
b0 ;
1"
#745000
0"
#750000
b11111110 !
b11111110 0
b11111110 9
b1 ;
1>
01
b10101 8
07
b0 )
b0 5
b0 ,
b0 3
b0 +
b0 4
b0 .
b0 2
0-
b0 6
0/
1"
#755000
0"
#760000
b11011100 !
b11011100 0
b11011100 9
b10100 8
b10 ;
b1111111000000000000000000000000000000000000000000000000000000000 &
b1111111000000000000000000000000000000000000000000000000000000000 =
1"
#765000
0"
#770000
b10111010 !
b10111010 0
b10111010 9
b11 ;
b1111111011011100000000000000000000000000000000000000000000000000 &
b1111111011011100000000000000000000000000000000000000000000000000 =
b10011 8
1"
#775000
0"
#780000
b10011000 !
b10011000 0
b10011000 9
b10010 8
b100 ;
b1111111011011100101110100000000000000000000000000000000000000000 &
b1111111011011100101110100000000000000000000000000000000000000000 =
1"
#785000
0"
#790000
b1110110 !
b1110110 0
b1110110 9
b101 ;
b1111111011011100101110101001100000000000000000000000000000000000 &
b1111111011011100101110101001100000000000000000000000000000000000 =
b10001 8
1"
#795000
0"
#800000
b1010100 !
b1010100 0
b1010100 9
b10000 8
b110 ;
b1111111011011100101110101001100001110110000000000000000000000000 &
b1111111011011100101110101001100001110110000000000000000000000000 =
1"
#805000
0"
#810000
b110010 !
b110010 0
b110010 9
b111 ;
b1111111011011100101110101001100001110110010101000000000000000000 &
b1111111011011100101110101001100001110110010101000000000000000000 =
b1111 8
1"
#815000
0"
#820000
b10000 !
b10000 0
b10000 9
b1110 8
b1000 ;
b1111111011011100101110101001100001110110010101000011001000000000 &
b1111111011011100101110101001100001110110010101000011001000000000 =
1"
#825000
0"
#830000
b0 !
b0 0
b0 9
b1001 ;
b1111111011011100101110101001100001110110010101000011001000010000 &
b1111111011011100101110101001100001110110010101000011001000010000 =
b1101 8
1"
#835000
0"
#840000
b1100 8
b1010 ;
1"
#845000
0"
#850000
b1011 ;
b1011 8
1"
#855000
0"
#860000
b110010 !
b110010 0
b110010 9
b1010 8
b1100 ;
1"
#865000
0"
#870000
b1011 !
b1011 0
b1011 9
b1101 ;
b110010 (
b110010 <
b1001 8
1"
#875000
0"
#880000
b1100 !
b1100 0
b1100 9
b1000 8
b1110 ;
1"
#885000
0"
#890000
b1101 !
b1101 0
b1101 9
b1111 ;
b111 8
1"
#895000
0"
#900000
b1110 !
b1110 0
b1110 9
b110 8
b10000 ;
1"
#905000
0"
#910000
b1111 !
b1111 0
b1111 9
b10001 ;
b101 8
1"
#915000
0"
#920000
b10000 !
b10000 0
b10000 9
b100 8
b10010 ;
1"
#925000
0"
#930000
b10001 !
b10001 0
b10001 9
b10011 ;
b11 8
1"
#935000
0"
#940000
b10010 !
b10010 0
b10010 9
b10 8
b10100 ;
1"
#945000
0"
#950000
b10011 !
b10011 0
b10011 9
b10101 ;
b1 8
1"
#955000
0"
#960000
b10100 !
b10100 0
b10100 9
11
b0 8
b10110 ;
1"
#965000
0"
#970000
b1011000 !
b1011000 0
b1011000 9
b10111 ;
0>
1'
b1 6
1"
#975000
0"
#980000
b11111110 !
b11111110 0
b11111110 9
b10 6
1>
b0 (
b0 <
b0 &
b0 =
b1 ;
0'
1"
#985000
0"
#990000
b11011100 !
b11011100 0
b11011100 9
b10 ;
b1111111000000000000000000000000000000000000000000000000000000000 &
b1111111000000000000000000000000000000000000000000000000000000000 =
b11 6
1"
#995000
0"
#1000000
b10111010 !
b10111010 0
b10111010 9
b100 6
b11 ;
b1111111011011100000000000000000000000000000000000000000000000000 &
b1111111011011100000000000000000000000000000000000000000000000000 =
1"
#1005000
0"
#1010000
b10011000 !
b10011000 0
b10011000 9
b100 ;
b1111111011011100101110100000000000000000000000000000000000000000 &
b1111111011011100101110100000000000000000000000000000000000000000 =
b101 6
1"
#1015000
0"
#1020000
b1110110 !
b1110110 0
b1110110 9
b110 6
b101 ;
b1111111011011100101110101001100000000000000000000000000000000000 &
b1111111011011100101110101001100000000000000000000000000000000000 =
1"
#1025000
0"
#1030000
b1010100 !
b1010100 0
b1010100 9
b110 ;
b1111111011011100101110101001100001110110000000000000000000000000 &
b1111111011011100101110101001100001110110000000000000000000000000 =
b111 6
1"
#1035000
0"
#1040000
b110010 !
b110010 0
b110010 9
b1000 6
b111 ;
b1111111011011100101110101001100001110110010101000000000000000000 &
b1111111011011100101110101001100001110110010101000000000000000000 =
1"
#1045000
0"
#1050000
b10000 !
b10000 0
b10000 9
b1000 ;
b1111111011011100101110101001100001110110010101000011001000000000 &
b1111111011011100101110101001100001110110010101000011001000000000 =
b1001 6
1"
#1055000
0"
#1060000
b0 !
b0 0
b0 9
b1010 6
b1001 ;
b1111111011011100101110101001100001110110010101000011001000010000 &
b1111111011011100101110101001100001110110010101000011001000010000 =
1"
#1065000
0"
#1070000
b1010 ;
b1011 6
1"
#1075000
0"
#1080000
b1100 6
b1011 ;
1"
#1085000
0"
#1090000
b110010 !
b110010 0
b110010 9
b1100 ;
b1101 6
1"
#1095000
0"
#1100000
b1011 !
b1011 0
b1011 9
b1110 6
b1101 ;
b110010 (
b110010 <
1"
#1105000
0"
#1110000
b1100 !
b1100 0
b1100 9
b1110 ;
b1111 6
1"
#1115000
0"
#1120000
b1101 !
b1101 0
b1101 9
b10000 6
b1111 ;
1"
#1125000
0"
#1130000
b1110 !
b1110 0
b1110 9
b10000 ;
b10001 6
1"
#1135000
0"
#1140000
b1111 !
b1111 0
b1111 9
b10010 6
b10001 ;
1"
#1145000
0"
#1150000
b10000 !
b10000 0
b10000 9
b10010 ;
b10011 6
1"
#1155000
0"
#1160000
b10001 !
b10001 0
b10001 9
b10100 6
b10011 ;
1"
#1165000
0"
#1170000
b10010 !
b10010 0
b10010 9
b10100 ;
b10101 6
1"
#1175000
0"
#1180000
b10011 !
b10011 0
b10011 9
b10110 6
b10101 ;
1"
#1185000
0"
